AUTHORS
CHANGELOG
MANIFEST.in
README.rst
pyproject.toml
setup.py
autosemver/__init__.py
autosemver/api.py
autosemver/git.py
autosemver/packaging.py
autosemver.egg-info/PKG-INFO
autosemver.egg-info/SOURCES.txt
autosemver.egg-info/dependency_links.txt
autosemver.egg-info/entry_points.txt
autosemver.egg-info/requires.txt
autosemver.egg-info/top_level.txt