Metadata-Version: 2.1
Name: autosemver
Version: 1.0.0
Summary: Tools to handle automatic semantic versioning in python
Home-page: https://github.com/david-caro/python-autosemver
Author: David Caro
Author-email: david@dcaro.es
License: GPLv3
Platform: UNKNOWN
